xanthus/__init__.py
xanthus/__main__.py
xanthus/version.py
xanthus/utils/__init__.py
xanthus/utils/chrome.py
xanthus/utils/x.py
zf_xanthus-0.1.6.dist-info/LICENSE
zf_xanthus-0.1.6.dist-info/METADATA
zf_xanthus-0.1.6.dist-info/WHEEL
zf_xanthus-0.1.6.dist-info/entry_points.txt
zf_xanthus-0.1.6.dist-info/top_level.txt
zf_xanthus-0.1.6.dist-info/RECORD
