Metadata-Version: 2.1
Name: zf-xanthus
Version: 0.1.6
Summary: xanthus generates weekly updates from X bookmarks
Author: Zeff Muks
Author-email: zeffmuks@gmail.com
License: Proprietary
Classifier: License :: Other/Proprietary License
Classifier: Programming Language :: Python :: 3
Classifier: Programming Language :: Python :: 3.11
License-File: LICENSE
Requires-Dist: backports.tarfile==1.2.0
Requires-Dist: browsercookie==0.7.9
Requires-Dist: greenlet==3.0.3
Requires-Dist: importlib-metadata==8.2.0
Requires-Dist: jaraco.classes==3.4.0
Requires-Dist: jaraco.context==5.3.0
Requires-Dist: jaraco.functools==4.0.2
Requires-Dist: keyring==25.3.0
Requires-Dist: loguru==0.7.2
Requires-Dist: lz4==4.3.3
Requires-Dist: more-itertools==10.3.0
Requires-Dist: playwright==1.45.1
Requires-Dist: pycryptodome==3.20.0
Requires-Dist: pyee==11.1.0
Requires-Dist: typing-extensions==4.12.2
Requires-Dist: zipp==3.19.2
